{
   "data": [
      {
         "task": "Assignment GUI",
         "quad": 1,
         "id": 102349368236127411
      },
      {
         "task": "Workout",
         "quad": 2,
         "id": 245232839412361278
      },
      {
         "task": "Cook",
         "quad": 3,
         "id": 170202480011583758
      },
      {
         "task": "Box",
         "quad": 4,
         "id": 327730183254113101
      },
      {
         "task": "Work on assistant program",
         "quad": 1,
         "id": 246604633663114823
      },
      {
         "task": "Test",
         "quad": 2,
         "id": 204398630354784246
      },
      {
         "task": "clean fridge",
         "quad": 3,
         "id": 538253263095936975
      },
      {
         "task": "leetcode",
         "quad": 4,
         "id": 774526737050442441
      }
   ]
}